stainless_demo/__init__.py
stainless_demo/_base_client.py
stainless_demo/_client.py
stainless_demo/_compat.py
stainless_demo/_constants.py
stainless_demo/_exceptions.py
stainless_demo/_files.py
stainless_demo/_models.py
stainless_demo/_qs.py
stainless_demo/_resource.py
stainless_demo/_response.py
stainless_demo/_streaming.py
stainless_demo/_types.py
stainless_demo/_version.py
stainless_demo/py.typed
stainless_demo/_utils/__init__.py
stainless_demo/_utils/_logs.py
stainless_demo/_utils/_proxy.py
stainless_demo/_utils/_reflection.py
stainless_demo/_utils/_streams.py
stainless_demo/_utils/_sync.py
stainless_demo/_utils/_transform.py
stainless_demo/_utils/_typing.py
stainless_demo/_utils/_utils.py
stainless_demo/lib/.keep
stainless_demo/resources/__init__.py
stainless_demo/resources/posts.py
stainless_demo/resources/users.py
stainless_demo/types/__init__.py
stainless_demo/types/post.py
stainless_demo/types/post_create_params.py
stainless_demo/types/post_list_params.py
stainless_demo/types/post_list_response.py
stainless_demo/types/post_update_params.py
stainless_demo/types/user.py
stainless_demo/types/user_create_params.py
stainless_demo/types/user_list_params.py
stainless_demo/types/user_list_response.py
stainless_demo/types/user_update_params.py
stainless_demo-0.0.1a1.dist-info/METADATA
stainless_demo-0.0.1a1.dist-info/WHEEL
stainless_demo-0.0.1a1.dist-info/licenses/LICENSE
stainless_demo-0.0.1a1.dist-info/RECORD
